random_gen.py
random_gen-1.0.0.dist-info/LICENSE
random_gen-1.0.0.dist-info/METADATA
random_gen-1.0.0.dist-info/WHEEL
random_gen-1.0.0.dist-info/top_level.txt
random_gen-1.0.0.dist-info/RECORD
