Metadata-Version: 2.1
Name: random-gen
Version: 1.0.0
Summary: Module to generate random numbers along a probability distribution
Home-page: https://github.com/hp310780/random-gen
Author: hp310780
License: MIT License
Platform: UNKNOWN
Classifier: Programming Language :: Python :: 3
